MANIFEST.in
README.md
setup.py
az_r2r.egg-info/PKG-INFO
az_r2r.egg-info/SOURCES.txt
az_r2r.egg-info/dependency_links.txt
az_r2r.egg-info/requires.txt
az_r2r.egg-info/top_level.txt
r2r/.DS_Store
r2r/__init__.py
r2r/config.json
r2r/__pycache__/__init__.cpython-311.pyc
r2r/base/__init__.py
r2r/base/__pycache__/__init__.cpython-311.pyc
r2r/base/abstractions/__init__.py
r2r/base/abstractions/base.py
r2r/base/abstractions/document.py
r2r/base/abstractions/llama_abstractions.py
r2r/base/abstractions/llm.py
r2r/base/abstractions/prompt.py
r2r/base/abstractions/search.py
r2r/base/abstractions/vector.py
r2r/base/abstractions/__pycache__/__init__.cpython-311.pyc
r2r/base/abstractions/__pycache__/base.cpython-311.pyc
r2r/base/abstractions/__pycache__/document.cpython-311.pyc
r2r/base/abstractions/__pycache__/llama_abstractions.cpython-311.pyc
r2r/base/abstractions/__pycache__/llm.cpython-311.pyc
r2r/base/abstractions/__pycache__/prompt.cpython-311.pyc
r2r/base/abstractions/__pycache__/search.cpython-311.pyc
r2r/base/abstractions/__pycache__/vector.cpython-311.pyc
r2r/base/logging/__init__.py
r2r/base/logging/kv_logger.py
r2r/base/logging/log_processor.py
r2r/base/logging/run_manager.py
r2r/base/logging/__pycache__/__init__.cpython-311.pyc
r2r/base/logging/__pycache__/kv_logger.cpython-311.pyc
r2r/base/logging/__pycache__/log_processor.cpython-311.pyc
r2r/base/logging/__pycache__/run_manager.cpython-311.pyc
r2r/base/parsers/__init__.py
r2r/base/parsers/base_parser.py
r2r/base/parsers/__pycache__/__init__.cpython-311.pyc
r2r/base/parsers/__pycache__/base_parser.cpython-311.pyc
r2r/base/pipeline/__init__.py
r2r/base/pipeline/base_pipeline.py
r2r/base/pipeline/__pycache__/__init__.cpython-311.pyc
r2r/base/pipeline/__pycache__/base_pipeline.cpython-311.pyc
r2r/base/pipes/__init__.py
r2r/base/pipes/base_pipe.py
r2r/base/pipes/__pycache__/__init__.cpython-311.pyc
r2r/base/pipes/__pycache__/base_pipe.cpython-311.pyc
r2r/base/providers/__init__.py
r2r/base/providers/base_provider.py
r2r/base/providers/embedding_provider.py
r2r/base/providers/eval_provider.py
r2r/base/providers/kg_provider.py
r2r/base/providers/llm_provider.py
